Best_Classification_Model/__init__.py
Best_Classification_Model/best_model.py
BestClassificationModel-0.1.2.dist-info/METADATA
BestClassificationModel-0.1.2.dist-info/WHEEL
BestClassificationModel-0.1.2.dist-info/top_level.txt
BestClassificationModel-0.1.2.dist-info/RECORD
