Metadata-Version: 2.1
Name: BestClassificationModel
Version: 0.1.2
Summary: It helps to find the best classification model with the accuracy based on the given dataset
Home-page: https://github.com/ronakkkk/best_classification_model
Author: Ronak Bhagchandani
Author-email: rishibhagchandani123@gmail.com
License: Apache License 2.0
Platform: UNKNOWN
Requires-Dist: sklearn
